NumpyChuxuezheZhinanZhongwenDisanbanChuyiFix1/README.md
NumpyChuxuezheZhinanZhongwenDisanbanChuyiFix1/__init__.py
NumpyChuxuezheZhinanZhongwenDisanbanChuyiFix1/__main__.py
NumpyChuxuezheZhinanZhongwenDisanbanChuyiFix1/file.epub
NumpyChuxuezheZhinanZhongwenDisanbanChuyiFix1/index.html
NumpyChuxuezheZhinanZhongwenDisanbanChuyiFix1/css/__init__.py
NumpyChuxuezheZhinanZhongwenDisanbanChuyiFix1/css/annotations.css
NumpyChuxuezheZhinanZhongwenDisanbanChuyiFix1/css/main.css
NumpyChuxuezheZhinanZhongwenDisanbanChuyiFix1/css/normalize.css
NumpyChuxuezheZhinanZhongwenDisanbanChuyiFix1/css/popup.css
NumpyChuxuezheZhinanZhongwenDisanbanChuyiFix1/font/__init__.py
NumpyChuxuezheZhinanZhongwenDisanbanChuyiFix1/font/fontello.eot
NumpyChuxuezheZhinanZhongwenDisanbanChuyiFix1/font/fontello.svg
NumpyChuxuezheZhinanZhongwenDisanbanChuyiFix1/font/fontello.ttf
NumpyChuxuezheZhinanZhongwenDisanbanChuyiFix1/font/fontello.woff
NumpyChuxuezheZhinanZhongwenDisanbanChuyiFix1/img/__init__.py
NumpyChuxuezheZhinanZhongwenDisanbanChuyiFix1/img/annotator-glyph-sprite.png
NumpyChuxuezheZhinanZhongwenDisanbanChuyiFix1/img/annotator-icon-sprite.png
NumpyChuxuezheZhinanZhongwenDisanbanChuyiFix1/img/apple-touch-icon.png
NumpyChuxuezheZhinanZhongwenDisanbanChuyiFix1/img/cancelfullscreen.png
NumpyChuxuezheZhinanZhongwenDisanbanChuyiFix1/img/close.png
NumpyChuxuezheZhinanZhongwenDisanbanChuyiFix1/img/fullscreen.png
NumpyChuxuezheZhinanZhongwenDisanbanChuyiFix1/img/loader.gif
NumpyChuxuezheZhinanZhongwenDisanbanChuyiFix1/img/menu-icon.png
NumpyChuxuezheZhinanZhongwenDisanbanChuyiFix1/img/save.png
NumpyChuxuezheZhinanZhongwenDisanbanChuyiFix1/img/saved.png
NumpyChuxuezheZhinanZhongwenDisanbanChuyiFix1/img/settings-s.png
NumpyChuxuezheZhinanZhongwenDisanbanChuyiFix1/img/settings.png
NumpyChuxuezheZhinanZhongwenDisanbanChuyiFix1/img/star.png
NumpyChuxuezheZhinanZhongwenDisanbanChuyiFix1/js/__init__.py
NumpyChuxuezheZhinanZhongwenDisanbanChuyiFix1/js/epub.js
numpy_chuxuezhe_zhinan_zhongwen_disanban_chuyi_fix1-2025.3.24.0.dist-info/METADATA
numpy_chuxuezhe_zhinan_zhongwen_disanban_chuyi_fix1-2025.3.24.0.dist-info/WHEEL
numpy_chuxuezhe_zhinan_zhongwen_disanban_chuyi_fix1-2025.3.24.0.dist-info/entry_points.txt
numpy_chuxuezhe_zhinan_zhongwen_disanban_chuyi_fix1-2025.3.24.0.dist-info/top_level.txt
numpy_chuxuezhe_zhinan_zhongwen_disanban_chuyi_fix1-2025.3.24.0.dist-info/RECORD
